generatepwd/__init__.py
generatepwd/cli.py
generatepwd/complexity.py
generatepwd/distribution.py
generatepwd/generator.py
generatepwd/main.py
generatepwd/password_exceptions.py
generatepwd/print_handler.py
generatepwd/validators.py
generatepwd-1.0.2.dist-info/METADATA
generatepwd-1.0.2.dist-info/WHEEL
generatepwd-1.0.2.dist-info/entry_points.txt
generatepwd-1.0.2.dist-info/top_level.txt
generatepwd-1.0.2.dist-info/RECORD
