Metadata-Version: 2.4
Name: generatepwd
Version: 1.0.2
Summary: A command-line password generator with customizable complexity levels
Author-email: Sriram Dhanaraj <sriramdvhere@gmail.com>
License: MIT
Project-URL: Homepage, https://github.com/sriramdvhere/generatepwd
Project-URL: Repository, https://github.com/sriramdvhere/generatepwd
Project-URL: Issues, https://github.com/sriramdvhere/generatepwd/issues
Keywords: password,generator,cli,security
Classifier: Development Status :: 4 - Beta
Classifier: Environment :: Console
Classifier: Intended Audience :: Developers
Classifier: Intended Audience :: End Users/Desktop
Classifier: License :: OSI Approved :: MIT License
Classifier: Operating System :: OS Independent
Classifier: Programming Language :: Python :: 3
Classifier: Programming Language :: Python :: 3.8
Classifier: Programming Language :: Python :: 3.9
Classifier: Programming Language :: Python :: 3.10
Classifier: Programming Language :: Python :: 3.11
Classifier: Programming Language :: Python :: 3.12
Classifier: Programming Language :: Python :: 3.13
Classifier: Topic :: Security
Classifier: Topic :: Utilities
Requires-Python: >=3.8
Requires-Dist: click>=8.0.0
Provides-Extra: dev
Requires-Dist: pytest>=6.0; extra == "dev"
Requires-Dist: black; extra == "dev"
Requires-Dist: flake8; extra == "dev"
Requires-Dist: mypy; extra == "dev"
